{"name":"WP zer0ptsCTF","slug":"WP-zer0ptsCTF","count":1,"postlist":[{"title":"zer0ptsWP","uid":"4e0d501b6d8004c9448da7812fda61ec","slug":"CTF/WP/zer0ptsWP","date":"2022-03-22T13:29:55.000Z","updated":"2022-03-22T13:49:20.875Z","comments":true,"path":"api/articles/CTF/WP/zer0ptsWP.json","keywords":null,"cover":"/img/36.jpg","text":" zer0pts题目复现先写两道密码一道web，另外两道密码还没看懂….等看懂了在写 Anti-Fermat题目如下 from Crypto.Util.number import isPrime, getStrongPrime from gmpy import next_prim...","link":"","photos":[],"count_time":{"symbolsCount":"15k","symbolsTime":"14 mins."},"categories":[{"name":"WP","slug":"WP","count":3,"path":"api/categories/WP.json"}],"tags":[{"name":"WP zer0ptsCTF","slug":"WP-zer0ptsCTF","count":1,"path":"api/tags/WP-zer0ptsCTF.json"}],"author":{"name":"S1eepy","slug":"blog-author","avatar":"/img/touxiang.jpg","link":"/","description":"Someone who is learning how to take life seriously","socials":{"github":"","twitter":"","stackoverflow":"","wechat":"","qq":"","weibo":"","zhihu":"","csdn":"","juejin":"","customs":{}}},"feature":true}]}